classgen/__init__.py
classgen/__main__.py
classgen/classgen/ClassGenerator.py
classgen/classgen/__init__.py
classgen-0.0.8.dist-info/LICENSE
classgen-0.0.8.dist-info/METADATA
classgen-0.0.8.dist-info/WHEEL
classgen-0.0.8.dist-info/top_level.txt
classgen-0.0.8.dist-info/RECORD
